{
  "meta": {
    "stableOrder": true
  },
  "lockfileVersion": 3,
  "ATTENTION": "THIS IS AN AUTOGENERATED FILE. DO NOT EDIT THIS FILE DIRECTLY.",
  "specifiers": {
    "libentry.so@src/main/cpp/types/libentry": "libentry.so@src/main/cpp/types/libentry",
    "libhello.so@src/main/cpp/types/libhello": "libhello.so@src/main/cpp/types/libhello",
    "libnapi.so@src/main/cpp/types/libnapi": "libnapi.so@src/main/cpp/types/libnapi",
    "libnapi_compact_mode.so@src/main/cpp/types/libnapi_compact_mode": "libnapi_compact_mode.so@src/main/cpp/types/libnapi_compact_mode"
  },
  "packages": {
    "libentry.so@src/main/cpp/types/libentry": {
      "name": "libentry.so",
      "version": "1.0.0",
      "resolved": "src/main/cpp/types/libentry",
      "registryType": "local"
    },
    "libhello.so@src/main/cpp/types/libhello": {
      "name": "libhello.so",
      "version": "1.0.0",
      "resolved": "src/main/cpp/types/libhello",
      "registryType": "local"
    },
    "libnapi.so@src/main/cpp/types/libnapi": {
      "name": "libnapi.so",
      "version": "1.0.0",
      "resolved": "src/main/cpp/types/libnapi",
      "registryType": "local"
    },
    "libnapi_compact_mode.so@src/main/cpp/types/libnapi_compact_mode": {
      "name": "libnapi_compact_mode.so",
      "version": "1.0.0",
      "resolved": "src/main/cpp/types/libnapi_compact_mode",
      "registryType": "local"
    }
  }
}